{
  "news": [
    {
      "id": 1,
      "title": "Berita Pertama",
      "description": "Ini adalah berita pertama",
      "date": "2025-07-07",
      "image_url": "https://example.com/image.jpg"
    },
    {
      "id": 2,
      "title": "Atlet Indonesia Raih Emas di Olimpiade",
      "description": "Atlet angkat besi Indonesia berhasil menyumbangkan medali emas pertama di Olimpiade 2025 di Paris.",
      "date": "2025-07-06",
      "image_url": "https://cdn0-production-images-kly.akamaized.net/8xgCmfEMWihVpG2nxUHTF7XulYc=/1200x675/smart/filters:quality(75):strip_icc():format(webp)/kly-media-production/medias/4255805/original/017128800_1666590311-shutterstock_2211031563.jpg"
    },
    {
      "id": 3,
      "title": "Jadwal Lengkap Liga 1 Indonesia Musim 2025/2026",
      "description": "PT LIB resmi merilis jadwal lengkap Liga 1 Indonesia musim 2025/2026 yang akan dimulai pada 15 Juli 2025.",
      "date": "2025-07-05",
      "image_url": "https://asset.kompas.com/crops/U9qvLZ9PcykOmG3RZK6SVKkm0-o=/0x0:780x390/750x500/data/photo/2022/08/24/6305ccfe80785.jpg"
    },
    {
      "id": 4,
      "title": "Persiapan Bojan Hodak Jelang Laga Uji Coba",
      "description": "Pelatih Bojan Hodak memastikan timnas dalam kondisi siap menghadapi laga uji coba penting melawan Malaysia.",
      "date": "2025-07-06",
      "image_url": "https://example.com/news-bojan.jpg"
    }
  ]
}
